lusid_web_app/__init__.py
lusid_web_app/__version__.py
lusid_web_app/api_client.py
lusid_web_app/configuration.py
lusid_web_app/exceptions.py
lusid_web_app/rest.py
lusid_web_app/api/__init__.py
lusid_web_app/api/access_api.py
lusid_web_app/api/articles_api.py
lusid_web_app/api/auditing_api.py
lusid_web_app/api/config_api.py
lusid_web_app/api/contacts_api.py
lusid_web_app/api/logging_api.py
lusid_web_app/api/personalisations_api.py
lusid_web_app/api/reconciliations_api.py
lusid_web_app/api/reports_api.py
lusid_web_app/api/roadmap_api.py
lusid_web_app/api/settings_api.py
lusid_web_app/api/tickets_api.py
lusid_web_app/models/__init__.py
lusid_web_app/models/audit_data.py
lusid_web_app/models/audit_data_summary.py
lusid_web_app/models/audit_entry.py
lusid_web_app/models/audit_entry_note.py
lusid_web_app/models/audit_process.py
lusid_web_app/models/audit_process_summary.py
lusid_web_app/models/client_config.py
lusid_web_app/models/contact.py
lusid_web_app/models/contact_properties_request.py
lusid_web_app/models/create_audit_entry_request.py
lusid_web_app/models/create_domain_request.py
lusid_web_app/models/currency_and_amount.py
lusid_web_app/models/hubspot_contact.py
lusid_web_app/models/hubspot_identity.py
lusid_web_app/models/hubspot_identity_profile.py
lusid_web_app/models/hubspot_response_property.py
lusid_web_app/models/hubspot_response_property_version.py
lusid_web_app/models/hubspot_support_article.py
lusid_web_app/models/hubspot_support_article_list.py
lusid_web_app/models/label_value_set.py
lusid_web_app/models/link.py
lusid_web_app/models/log_level.py
lusid_web_app/models/lusid_problem_details.py
lusid_web_app/models/lusid_validation_problem_details.py
lusid_web_app/models/mapping.py
lusid_web_app/models/mapping_comparison_type.py
lusid_web_app/models/mapping_rule.py
lusid_web_app/models/metric_value.py
lusid_web_app/models/mixpanel.py
lusid_web_app/models/okta_config.py
lusid_web_app/models/perpetual_property.py
lusid_web_app/models/personalisation.py
lusid_web_app_sdk_preview-0.4.1357.dist-info/METADATA
lusid_web_app_sdk_preview-0.4.1357.dist-info/WHEEL
lusid_web_app_sdk_preview-0.4.1357.dist-info/top_level.txt
lusid_web_app_sdk_preview-0.4.1357.dist-info/RECORD
