Metadata-Version: 2.1
Name: lusid-web-app-sdk-preview
Version: 0.4.1357
Summary: Python Preview SDK for Web App API
Home-page: https://github.com/finbourne/lusid-web-app-sdk-python-preview
Author: FINBOURNE Technology
Author-email: engineering@finbourne.com
License: MIT
Keywords: OpenAPI,FINBOURNE,LUSID,Web App API
Platform: UNKNOWN
Requires-Dist: urllib3 (>=1.15)
Requires-Dist: six (>=1.10)
Requires-Dist: certifi (>=14.05.14)
Requires-Dist: python-dateutil (>=2.5.3)
Requires-Dist: urllib3 (>=1.15.1)
Requires-Dist: requests (>=2.21.0)
